{
	"DFFlagUseKeyframeHumanoidAnimations": "True",
	"AllowVideoPreRoll": true,
	"FFlagWaterEnabled": "True",
	"FFlagServerScriptProtection": "False",
	"FFlagTaskSchedulerUseSharedPtr": "True",
	"FFlagReparentingLockEnabled": "False",
	"FFlagDeprecateMeaninglessTerrainPropertiesAndMethods": "False",
	"FLogAsserts": "1",
	"NonScriptableAccessEnabled": "True",
	"FFlagNonScriptableAccessEnabled": "True",
	"FFlagUsesNewCameraFrustum": "False",
	"FLogCloseDataModel": "3",
	"FFlagImmediateYieldResultsEnabled": "True",
	"FFlagIsChangeHistoryRunAware": "True",
	"FFlagDisplayFPS": "False",
	"FFlagDE4411Fixed": "True",
	"FFlagAreSoundsFiltered": "False",
	"FFlagDE4510Fixed": "True",
	"FFlagDE4528Fixed": "True",
	"FFlagDE4508Fixed": "False",
	"FFlagFastClone": "False",
	"CaptureQTStudioCountersEnabled": "True",
	"CaptureMFCStudioCountersEnabled": "True",
	"CaptureCountersIntervalInMinutes": "5",
	"FFlagLoadingGuiEnabled": "True",
	"FLogServiceVectorResize": "4",
	"FLogServiceCreation": "4",
	"FFlagDMFeatherweightEnabled": "True",
	"FFlagRenderFeatherweightEnabled": "True",
	"FFlagRenderFeatherweightUseGeometryGenerator": "True",
	"FFlagRenderNoDMLock": "True",
	"FFlagFRMCullDebris": "True",
	"FFlagMouseMoveOptimization": "True",
	"FFlagDisableClickToWalk": "False",
	"FFlagSegregatedLuaEnvironments": "True",
	"FFlagInGamePurchases": "True",
	"FFlagOpenNativeBrowserWindowFromLua": "True",
	"FFlagRenderFlexClusterEnabled": "False",
	"ReorderGUI": "False",
	"FFlagRenderTextureCompositorUse32Bit": "True",
	"FFlagScriptAutoIndent": "True",
	"FFlagRenderShadowFadeout": "True",
	"FFlagDE3737Fixed": "True",
	"FFlagFRMUsePerformanceLockstepTable": "False",
	"FFlagD3D9UseSoftwareVertexShaders": "True",
	"FFlagRenderFastClusterParts": "True",
	"FFlagRenderFastClusterHumanoids": "True",
	"FFlagFRMForceShadingQualityIfShadowAll": "False",
	"FFlagUpdateTargetPointBeforeMouseDown": "True",
	"FFlagRenderFeatherweightForHighQuality": "False",
	"FFlagQtStudioHighlightAdornments": "True",
	"FFlagQtStudioToggleCollisionCheck": "True",
	"FFlagRobloxStudio2013MessageEnabled": "True",
	"FFlagDrawSelectionBoxLinesFarAway": "True",
	"FFlagThrottleIfNotFocus": "True",
	"AxisAdornmentGrabSize": "8",
	"FFlagProcessAllPacketsPerStep": "True",
	"FFlagImmediateCrashUploadEnabled": "True",
	"FFlagImmediateHangUploadEnabled": "True",
	"FFlagQTStudioDoNotDeleteWebDlg": "True",
	"FFlagQTStudioDoNotRedirect": "True",
	"FFlagFilterInvisibleNonCollidePartsInLadderRaycasts": "True",
	"FFlagScriptToggleFold": "True",
	"FFlagScriptCommentSelection": "True",
	"FFlagUS14116": "True",
	"FFlagRenderFastClusterForceSleepForFixed": "True",
	"FFlagFRMAdornSupport": "True",
	"FFlagEThrottleBumpUp": "True",
	"FFlagEditModeLaunchFromWebsiteEnabled": "False",
	"FFlagCameraJitterFix": "True",
	"FFlagShowSplashScreen": "True",
	"FFlagSkipBroadPhaseWhenThrottling": "True",
	"FFlagConsistentThrottlingIncrements": "True",
	"FFlagBlockBlockNarrowPhaseRefactor": "True",
	"FFlagClampEdgeEdgeConnectorPointsToEdges": "True",
	"FFlagPolyPolyFaceFacePairUsesAlternativeFace": "True",
	"FFlagFreeFallOptimization": "True",
	"FFlagImpulseSolverForContact": "True",
	"FFlagReduceToleranceToEdgeEdgeParallelism": "True",
	"FFlagEnableSixDigitDoublePrecision": "True",
	"FFlagQtStudioCreateJointsAutomatically": "True",
	"FFlagFriendlyErrorMsgOnStartGameFailure": "False",
	"FFlagQtStudioVideoRecordingEnabled": "True",
	"FFlagEnableRubberBandSelection": "True",
	"FFlagQtStudioScreenshotEnabled": "True",
	"FFlagClickDrillDown": "True",
	"FFlagFixNoPhysicsGlitchWithGyro": "True",
	"FFlagFixFirstPersonToolLag": "True",
	"FFlagUS14597": "True",
	"FFlagActOnUS14597": "True",
	"FFlagUseVirtualMethodForCellCallback": "True",
	"FFlagTurnOffUnthrottledLogs": "False",
	"FLogFullRenderObjects": "0",
	"FLogRenderFastCluster": "0",
	"PublishedProjectsPageHeight": "535",
	"PublishedProjectsPageUrl": "/ide/publish",
	"StartPageUrl": "/ide/welcome",
	"FFlagOpenNewWindowsInDefaultBrowser": "True",
	"FFlagOnScreenProfiler": "False",
	"FFlagUS14933": "True",
	"FFlagActOnUS14933": "True",
	"FFlagInitializeNewPlace": "True",
	"FFlagQtFileOpenCrashFix": "True",
	"FFlagWaitUntilSignalForJavascriptInit": "True",
	"FFlagQtStudioCrashCounters": "True",
	"MinNumberScriptExecutionsToGetPrize": 500,
	"FFlagUS15154": "True",
	"FFlagActOnUS15154": "True",
	"FFlagValidateAssetUrlEnabled": "False",
	"FFlagDebugCrashEnabled": "False",
	"FFlagRenderFastClusterHighQuality": "True",
	"FLogHangDetection": "3",
	"FFlagRenderFastClusterMergeDraws": "True",
	"FFlagRenderFastClusterMergeBuffers": "True",
	"FFlagVoxelGridInsideMegaCluster": "True",
	"FFlagRenderForceBevelsOff": "True",
	"FFlagRenderLightGridTerrainOccupancy": "False",
	"FFlagRenderOptimizedTextureUpload": "True",
	"FFlagCharAnimationStats": "False",
	"FFlagRenderOpenGLForcePOTTextures": "True",
	"FFlagUseNewCameraZoomPath": "True",
	"FFlagQTStudioPublishFailure": "True",
	"ExcludeContactWithInteriorTerrainMinusYFace": "True",
	"FFlagFixUphillClimb": "True",
	"FFlagUseAveragedFloorHeight": "True",
	"FFlagScaleExplosionLifetime": "True",
	"FFlagUS15300": "True",
	"PublishedProjectsPageWidth": "950",
	"FFlagRenderFastClusterEverywhere": "True",
	"FLogPlayerShutdownLuaTimeoutSeconds": "",
	"FFlagUS15977": "True",
	"FFlagQtFixToolDragging": "True",
	"FFlagSelectPartOnUndoRedo": "True",
	"FFlagUS15884": "True",
	"FFlagStatusBarProgress": "True",
	"FFlagStudioCheckForUpgrade": "True",
	"FFlagStudioInsertModelCounterEnabled": "True",
	"FFlagStudioAuthenticationFailureCounterEnabled": "True",
	"FFlagRenderCheckTextureContentProvider": "True",
	"FFlagRenderLightGridEnabled": "True",
	"FFlagStudioLightGridAPIVisible": "True",
	"FFlagActOnUS15526": "False",
	"FFlagUS15526": "True",
	"FFlagBetterSleepingJobErrorComputation": "True",
	"FFlagActOnUS15977": "False",
	"FLogDXVideoMemory": "4",
	"FFlagRenderNoLegacy": "True",
	"FFlagStudioLightGridOnForNewPlaces": "True",
	"FFlagPhysicsSkipRedundantJoinAll": "True",
	"FFlagTerrainOptimizedLoad": "True",
	"FFlagTerrainOptimizedStorage": "True",
	"FFlagTerrainOptimizedCHS": "True",
	"FFlagRenderGLES2": "True",
	"FFlagStudioMacAddressValidationEnabled": "True",
	"FFlagDoNotPassSunkEventsToPlayerMouse": "True",
	"FFlagQtAutoSave": "True",
	"FFlagRenderLoopExplicit": "True",
	"FFlagStudioUseBinaryFormatForPlay": "False",
	"PhysicsRemoveWorldAssemble_US16512": "False",
	"FFlagNativeSafeChatRendering": "True",
	"FFlagUS17162": "True",
	"DFFlagUS17412": "True",
	"FFlagRenderNewMegaCluster": "True",
	"FFlagAutoJumpForTouchDevices": "True",
	"DFFlagUS17646": "True",
	"DFFlagUS17889": "True",
	"FLogOutlineBrightnessMin": "50",
	"FLogOutlineBrightnessMax": "160",
	"FLogOutlineThickness": "40",
	"FFlagDE5511FixEnabled": "True",
	"FFlagDE4423Fixed": "True",
	"FFlagSymmetricContact": "True",
	"FFlagLocalMD5": "True",
	"FFlagStudioCookieParsingDisabled": "False",
	"FFlagLastWakeTimeSleepingJobError": "True",
	"FFlagPhysicsAllowAutoJointsWithSmallParts_DE6056": "True",
	"FFlagPhysicsLockGroupDraggerHitPointOntoSurface_DE6174": "True",
	"FFlagOutlineControlEnabled": "True",
	"FFlagAllowCommentedScriptSigs": "False",
	"FFlagDataModelUseBinaryFormatForSave": "True",
	"FFlagStudioUseBinaryFormatForSave": "True",
	"FFlagDebugAdornableCrash": "True",
	"FFlagOverlayDataModelEnabled": "True",
	"DFFlagFixInstanceParentDesyncBug": "True",
	"FFlagPromoteAssemblyModifications": "False",
	"FFlagFontSourceSans": "True",
	"DFFlagCreateHumanoidRootNode": "True",
	"FFlagRenderNewFonts": "True",
	"FFlagStudioCookieDesegregation": "True",
	"FFlagResponsiveJump": "True",
	"FFlagGoogleAnalyticsTrackingEnabled": "True",
	"FFlagNoCollideLadderFilter": "True",
	"FFlagFlexibleTipping": "True",
	"FFlagUseStrongerBalancer": "True",
	"FFlagClampControllerVelocityMag": "True",
	"DFFlagUseSaferChatMetadataLoading": "True",
	"FFlagSinkActiveGuiObjectMouseEvents": "False",
	"FLogLuaBridge": "2",
	"DFFlagPromoteAssemblyModifications": "True",
	"FFlagDeferredContacts": "True",
	"FFlagFRMUse60FPSLockstepTable": "True",
	"FFlagFRMAdjustForMultiCore": "True",
	"FFlagPhysics60HZ": "True",
	"FFlagQtRightClickContextMenu": "True",
	"FFlagUseTopmostSettingToBringWindowToFront": "True",
	"FFlagNewLightAPI": "True",
	"FFlagRenderLightGridShadows": "True",
	"FFlagRenderLightGridShadowsSmooth": "True",
	"DFFlagSanitizeKeyframeUrl": "True",
	"DFFlagDisableGetKeyframeSequence": "False",
	"FFlagCreateServerScriptServiceInStudio": "True",
	"FFlagCreateServerStorageInStudio": "True",
	"FFlagCreateNando": "True",
	"FFlagCreateReplicatedStorageInStudio": "True",
	"FFlagFilterEmoteChat": "True",
	"DFFlagUseCharacterRootforCameraTarget": "True",
	"FFlagImageRectEnabled": "True",
	"FFlagNewWaterMaterialEnable": "True",
	"DFFlagUserHttpAPIEnabled": "True",
	"DFIntUserHttpAccessUserId0": "62461124",
	"FFlagUserHttpAPIVisible": "True",
	"FFlagCameraChangeHistory": "True",
	"FFlagDE4640Fixed": "True",
	"FFlagShowStreamingEnabledProp": "True",
	"FFlagOptimizedDragger": "True",
	"FFlagRenderNewMaterials": "True",
	"FFlagRenderAnisotropy": "True",
	"FFlagStudioInitializeViewOnPaint": "True",
	"DFFlagPartsStreamingEnabled": "True",
	"FFlagStudioLuaDebugger": "True",
	"FFlagStudioLocalSpaceDragger": "True",
	"FFlagGuiRotationEnabled": "True",
	"FFlagDataStoreEnabled": "True",
	"DFFlagDisableTeleportConfirmation": "False",
	"DFFlagAllowTeleportFromServer": "True",
	"DFFlagNonBlockingTeleport": "True",
	"FFlagD3D9CrashOnError": "False",
	"FFlagRibbonBarEnabled": "True",
	"SFFlagInfiniteTerrain": "True",
	"FFlagStudioScriptBlockAutocomplete": "True",
	"FFlagRenderFixAnchoredLag": "True",
	"DFFlagAllowAllUsersToUseHttpService": "True",
	"GoogleAnalyticsAccountPropertyIDClient": "",
	"FFlagSurfaceGuiVisible": "True",
	"FFlagStudioIntellesenseEnabled": "True",
	"FFlagAsyncPostMachineInfo": "True",
	"FFlagModuleScriptsVisible": "True",
	"FFlagModelPluginsEnabled": "True",
	"FFlagGetUserIdFromPluginEnabled": "True",
	"FFlagStudioPluginUIActionEnabled": "True",
	"DFFlagRemoveAdornFromBucketInDtor": "True",
	"FFlagRapidJSONEnabled": "True",
	"DFFlagDE6959Fixed": "True",
	"DFFlagScopedMutexOnJSONParser": "True",
	"FFlagSupressNavOnTextBoxFocus": "True",
	"DFFlagExplicitPostContentType": "True",
	"DFFlagAddPlaceIdToAnimationRequests": "True",
	"FFlagCreatePlaceEnabled": "True",
	"DFFlagClientAdditionalPOSTHeaders": "True",
	"FFlagEnableAnimationExport": "True",
	"DFFlagAnimationAllowProdUrls": "True",
	"FFlagGetUserIDFromPluginEnabled": "True",
	"FFlagStudioContextualHelpEnabled": "True",
	"FFlagLogServiceEnabled": "True",
	"FFlagQtPlaySoloOptimization": "True",
	"FFlagStudioBuildGui": "True",
	"DFFlagListenForZVectorChanges": "True",
	"DFFlagUserInputServiceProcessOnRender": "True",
	"FFlagDE7421Fixed": "True",
	"FFlagStudioExplorerActionsEnabledInScriptView": "True",
	"FFlagHumanoidNetworkOptEnabled": "True",
	"DFFlagEnableNPCServerAnimation": "True",
	"DFFlagDataStoreUseUForGlobalDataStore": "True",
	"DFFlagDataStoreAllowedForEveryone": "True",
	"DFFlagBadTypeOnConnectErrorEnabled": "True",
	"FFlagStudioRemoveUpdateUIThread": "True",
	"FFlagPhysicsSkipUnnecessaryContactCreation": "False",
	"FFlagUseNewHumanoidCache": "True",
	"FFlagSecureReceiptsBackendEnabled": "False",
	"FFlagOrderedDataStoreEnabled": "True",
	"FFlagStudioLuaDebuggerGA": "True",
	"FFlagNPSSetScriptDocsReadOnly": "False",
	"FFlagRDBGHashStringComparison": "True",
	"FFlagStudioDebuggerVisitDescendants": "True",
	"FFlagDeprecateScriptInfoService": "False",
	"FFlagIntellisenseScriptContextDatamodelSearchingEnabled": "True",
	"FFlagStudioCompareDatamodelHashOnClose": "True",
	"FFlagSecureReceiptsFrontendEnabled": "True",
	"DFFlagCreatePlaceEnabledForEveryone": "True",
	"FFlagCreatePlaceInPlayerInventoryEnabled": "True",
	"DFFlagAddRequestIdToDeveloperProductPurchases": "True",
	"DFFlagUseYPCallInsteadOfPCallEnabled": "True",
	"FFlagStudioMouseOffsetFixEnabled": "True",
	"DFFlagPlaceValidation": "False",
	"FFlagHeapValuePointerXorEnabled": "True",
	"FFlagReconstructAssetUrl": "True",
	"FFlagUseNewSoundEngine": "True",
	"FIntMinMillisecondLengthForLongSoundChannel": "5000",
	"FFlagStudioHideInsertedServices": "True",
	"FFlagStudioAlwaysSetActionEnabledState": "True",
	"FFlagRenderNew": "True",
	"FIntRenderNewPercentWin": "100",
	"FIntRenderNewPercentMac": "100",
	"FLogGraphics": "6",
	"FFlagStudioInSyncWebKitAuthentication": "False",
	"DFFlagDisallowHopperServerScriptReplication": "False",
	"FFlagInterpolationFix": "False",
	"FFlagHeartbeatAt60Hz": "False",
	"DFFlagFixProcessReceiptValueTypes": "True",
	"DFFlagPhysicsSkipUnnecessaryContactCreation": "True",
	"FFlagStudioLiveCoding": "True",
	"FFlagPlayerHumanoidStep60Hz": "True",
	"DFFlagCrispFilteringEnabled": "False",
	"SFFlagProtocolSynchronization": "True",
	"FFlagUserInputServicePipelineStudio": "True",
	"FFlagUserInputServicePipelineWindowsClient": "True",
	"FFlagUserInputServicePipelineMacClient": "True",
	"FFlagStudioKeyboardMouseConfig": "True",
	"DFFlagLogServiceEnabled": "True",
	"DFFlagLoadAnimationsThroughInsertService": "True",
	"FFlagFRMFogEnabled": "True",
	"FLogBrowserActivity": "3",
	"DFFlagPhysicsPacketAlwaysUseCurrentTime": "True",
	"FFlagFixedStudioRotateTool": "False",
	"FFlagRibbonBarEnabledGA": "True",
	"FFlagRenderSafeChat": "True",
	"DFFlagPhysicsAllowSimRadiusToDecreaseToOne": "True",
	"DFFlagPhysicsAggressiveSimRadiusReduction": "True",
	"DFFlagLuaYieldErrorNoResumeEnabled": "True",
	"DFFlagEnableJointCache": "False",
	"DFFlagOnCloseTimeoutEnabled": "False",
	"FFlagStudioQuickInsertEnabled": "True",
	"FFlagStudioPropertiesRespectCollisionToggle": "True",
	"FFlagTweenServiceUsesRenderStep": "True",
	"FFlagUseNewSoundEngine3dFix": "True",
	"FFlagDebugUseDefaultGlobalSettings": "True",
	"FFlagStudioMiddleMouseTrackCamera": "False",
	"FFlagTurnOffiOSNativeControls": "True",
	"DFFlagUseNewHumanoidHealthGui": "True",
	"FFlagUS21919": "True",
	"DFFlagLoggingConsoleEnabled": "True",
	"DFFlagAllowModuleLoadingFromAssetId": "True",
	"FFlagStudioZoomExtentsExplorerFixEnabled": "True",
	"FFlagStudioExplorerFilterEnabled": "True",
	"FFlagStudioPropertySearchDisabled": "False",
	"FFlagLuaDebuggerBreakOnError": "True",
	"FFlagRetentionTrackingEnabled": "True",
	"FFlagShowAlmostAllItemsInExplorer": "True",
	"FFlagStudioFindInAllScriptsEnabled": "True",
	"FFlagImprovedNameOcclusion": "True",
	"FFlagHumanoidMoveToDefaultValueEnabled": "True",
	"FFlagEnableDisplayDistances": "True",
	"FFlagUseMinMaxZoomDistance": "True",
	"SFFlagAllowPhysicsPacketCompression": "False",
	"FFlagStudioOneClickColorPickerEnabled": "True",
	"DFFlagHumanoidMoveToDefaultValueEnabled": "True",
	"FFlagStudioFindContextFixEnabled": "False",
	"VideoPreRollWaitTimeSeconds": 45,
	"FFlagBalancingRateLimit": "True",
	"FFlagLadderCheckRate": "True",
	"FFlagStateSpecificAutoJump": "True",
	"SFFlagOneWaySimRadiusReplication": "True",
	"DFFlagApiDictionaryCompression": "True",
	"SFFlagPathBasedPartMovement": "True",
	"FFlagEnsureInputIsCorrectState": "False",
	"DFFlagLuaLoadStringStrictSecurity": "False",
	"DFFlagCrossPacketCompression": "True",
	"FFlagWorkspaceLoadStringEnabledHidden": "True",
	"FFlagStudioPasteAsSiblingEnabled": "True",
	"FFlagStudioDuplicateActionEnabled": "True",
	"FFlagPreventInterpolationOnCFrameChange": "True",
	"FLogNetworkPacketsReceive": 5,
	"FLogNetworkReadItem": 5,
	"FFlagPlayPauseFix": "True",
	"DFFlagCrashOnNetworkPacketError": "False",
	"FFlagHumanoidStateInterfaces": "True",
	"FFlagRenderDownloadAssets": "False",
	"FFlagBreakOnErrorConfirmationDialog": "True",
	"FFlagStudioAnalyticsEnabled": "True",
	"FFlagAutoRotateFlag": "True",
	"DFFlagUseImprovedLadderClimb": "True",
	"FFlagUseCameraOffset": "True",
	"FFlagRenderBlobShadows": "True",
	"DFFlagWebParserDisableInstances": "False",
	"FFlagStudioNewWiki": "True",
	"DFFlagLogPacketErrorDetails": "False",
	"FFlagStudioLiveColorProperty": "False",
	"FFlagLimitHorizontalDragForce": "True",
	"FFlagEnableNonleathalExplosions": "True",
	"DFFlagCreateSeatWeldOnServer": "True",
	"FFlagGraphicsUseRetina": "True",
	"FFlagDynamicEnvmapEnabled": "True",
	"DFFlagDeferredTouchReplication": true,
	"DFFlagCreatePlayerGuiEarlier": "True",
	"DFFlagProjectileOwnershipOptimization": "True",
	"DFFlagLoadSourceForCoreScriptsBeforeInserting": "False",
	"GoogleAnalyticsLoadStudio": 1,
	"DFFlagTaskSchedulerFindJobOpt": "True",
	"SFFlagPreventInterpolationOnCFrameChange": "True",
	"DFIntNumPhysicsPacketsPerStep": 2,
	"DFFlagDataStoreUrlEncodingEnabled": "True",
	"FFlagShowWebPlaceNameOnTabWhenOpeningFromWeb": "True",
	"DFFlagTrackTimesScriptLoadedFromLinkedSource": "True",
	"FFlagToggleDevConsoleThroughChatCommandEnabled": "False",
	"FFlagEnableFullMonitorsResolution": "True",
	"DFFlagAlwaysUseHumanoidMass": "True",
	"DFFlagUseStrongerGroundControl": "True",
	"DFFlagCorrectlyReportSpeedOnRunStart": "True",
	"FFlagLuaDebuggerImprovedToolTip": "True",
	"FFlagLuaDebuggerPopulateFuncName": "True",
	"FFlagLuaDebuggerNewCodeFlow": "True",
	"DFFlagValidateCharacterAppearanceUrl": "True",
	"FFlagStudioQuickAccessCustomization": "True",
	"DFFlagTaskSchedulerUpdateJobPriorityOnWake": "True",
	"DFFlagTaskSchedulerNotUpdateErrorOnPreStep": "True",
	"FFlagWikiSelectionSearch": "True",
	"DFIntTaskSchedularBatchErrorCalcFPS": 1200,
	"FFlagSuppressNavOnTextBoxFocus": "False",
	"FFlagEnabledMouseIconStack": "True",
	"DFFlagFastClone": "True",
	"DFFlagLuaNoTailCalls": "True",
	"DFFlagFilterStreamingProps": "True",
	"DFFlagNetworkOwnerOptEnabled": "False",
	"DFFlagPathfindingEnabled": "True",
	"FFlagEnableiOSSettingsLeave": "True",
	"FFlagUseFollowCamera": "True",
	"FFlagDefaultToFollowCameraOnTouch": "True",
	"DFFlagAllowMoveToInMouseLookMove": "True",
	"DFFlagAllowHumanoidDecalTransparency": "True",
	"DFFlagSupportCsrfHeaders": "True",
	"DFFlagConfigureInsertServiceFromSettings": "True",
	"FFlagPathfindingClientComputeEnabled": "True",
	"DFFlagLuaResumeSupportsCeeCalls": "True",
	"DFFlagPhysicsSenderErrorCalcOpt": "True",
	"DFFlagClearPlayerReceivingServerLogsOnLeave": "False",
	"DFFlagConsoleCodeExecutionEnabled": "False",
	"DFFlagCSGDictionaryReplication": "True",
	"FFlagCSGToolsEnabled": "True",
	"FFlagCSGDictionaryServiceEnabled": "True",
	"FFlagCSGMeshRenderEnable": "True",
	"FFlagCSGChangeHistory": "True",
	"FFlagCSGMeshColorEnable": "True",
	"FFlagCSGMeshColorToolsEnabled": "True",
	"FFlagCSGScaleEnabled": "True",
	"FFlagCylinderUsesConstantTessellation": "True",
	"FFlagStudioDraggersScaleFixes": "True",
	"FFlagCSGDecalsEnabled": "True",
	"FFlagCSGMigrateChildData": "False",
	"SFFlagBinaryStringReplicationFix": "True",
	"FFlagHummanoidScaleEnable": "True",
	"FFlagStudioDataModelIsStudioFix": "True",
	"DFFlagWebParserEnforceASCIIEnabled": "True",
	"DFFlagScriptDefaultSourceIsEmpty": "True",
	"FFlagFixCaptureFocusInput": "True",
	"FFlagFireUserInputServiceEventsAfterDMEvents": "True",
	"FFlagVectorErrorOnNilArithmetic": "True",
	"FFlagFontSmoothScalling": "True",
	"DFFlagUseImageColor": "True",
	"FFlagStopNoPhysicsStrafe": "True",
	"DFFlagDebugLogNetworkErrorToDB": "False",
	"FFlagLowQMaterialsEnable": "True",
	"FFLagEnableFullMonitorsResolution": "True",
	"FFlagStudioChildProcessCleanEnabled": "True",
	"DFFlagAllowFullModelsWhenLoadingModules": "True",
	"DFFlagRealWinInetHttpCacheBypassingEnabled": "True",
	"FFlagNewUniverseInfoEndpointEnabled": "True",
	"FFlagGameExplorerEnabled": "True",
	"FFlagStudioUseBinaryFormatForModelPublish": "True",
	"FFlagGraphicsFeatureLvlStatsEnable": "True",
	"FFlagStudioEnableWebKitPlugins": "True",
	"DFFlagSendHumanoidTouchedSignal": "True",
	"DFFlagReduceHumanoidBounce": "True",
	"DFFlagUseNewSounds": "True",
	"FFlagFixHumanoidRootPartCollision": "True",
	"FFlagEnableAndroidMenuLeave": "True",
	"FFlagOnlyProcessGestureEventsWhenSunk": "True",
	"FFlagAdServiceReportImpressions": "True",
	"FFlagStudioUseExtendedHTTPTimeout": "True",
	"FFlagStudioSeparateActionByActivationMethod": "False",
	"DFFlagPhysicsSenderThrottleBasedOnBufferHealth": "True",
	"FFlagCSGExportFailure": "False",
	"DFFlagGetGroupInfoEnabled": "True",
	"DFFlagGetGroupRelationsEnabled": "True",
	"FStringPlaceFilter_StateBasedAnimationReplication": "True;175953385;174810327;181219650",
	"SFFlagTopRepContSync": "True",
	"FFlagStudioUseBinaryFormatForModelSave": "False",
	"EnableFullMonitorsResolution": "True",
	"DFFlagRenderSteppedServerExceptionEnabled": "True",
	"FFlagUseWindowSizeFromGameSettings": "True",
	"DFFlagCheckStudioApiAccess": "True",
	"FFlagGameExplorerPublishEnabled": "True",
	"FFlagFramerateVisualizerReport": "True",
	"DFFlagKeepXmlIdsBetweenLoads": "True",
	"DFFlagReadXmlCDataEnabled": "True",
	"FFlagStudioRemoveToolSounds": "True",
	"FFlagStudioOneStudGridDefault": "True",
	"FFlagStudioPartSymmetricByDefault": "True",
	"FFlagStudioIncreasedBaseplateSize": "True",
	"FFlagTaskSchedulerCyclicExecutive": "False",
	"FFlagSkipSilentAudioOps": "True",
	"SFFlagGuid64Bit": "False",
	"FIntValidateLauncherPercent": "100",
	"FFlagCSGDataLossFixEnabled": "True",
	"DFStringRobloxAnalyticsURL": "http://public.ecs.roblox.com/",
	"DFFlagRobloxAnalyticsTrackingEnabled": "True",
	"FFlagStudioOpenFirstPlace": "False",
	"FFlagStudioOpenLastSaved": "False",
	"FFlagStudioShowTutorialsByDefault": "True",
	"FFlagStudioForceToolboxSize": "True",
	"FFlagStudioExplorerDisabledByDefault": "True",
	"FFlagStudioDefaultWidgetSizeChangesEnabled": "True",
	"FFlagStudioUseScriptAnalyzer": "True",
	"FFlagNoClimbPeople": "True",
	"DFFlagAnimationFormatAssetId": "True",
	"FFlagStudioMobileCompanionEnabled": "True",
	"FFlagGetCorrectScreenResolutionFaster": "True",
	"DFFlagFixTouchEndedReporting": "False",
	"FFlagStudioOpenFirstPlaceBasePlate": "False",
	"FFlagStudioTeleportPlaySolo": "True",
	"FFlagCSGRemoveScriptScaleRestriction": "True",
	"FFlagStudioDE7928FixEnabled": "True",
	"FFlagDE8768FixEnabled": "True",
	"FFlagStudioDE9108FixEnabled": "True",
	"FFlagStudioPlaySoloMapDebuggerData": "True",
	"FFlagLuaDebuggerCloneDebugger": "True",
	"FFlagStudioCommandLineSaveEditText": "False",
	"FFlagRenderLightgridInPerformEnable": "True",
	"SFFlagStateBasedAnimationReplication": "False",
	"FFlagVolumeControlInGameEnabled": "True",
	"FFlagGameConfigurerUseStatsService": "True",
	"FFlagStudioUseHttpAuthentication": "False",
	"FFlagDetectTemplatesWhenSettingUpGameExplorerEnabled": "True",
	"FFlagEntityNameEditingEnabled": "True",
	"FFlagNewCreatePlaceFlowEnabled": "True",
	"FFlagFakePlayableDevices": "False",
	"FFlagMutePreRollSoundService": "True",
	"DFFlagBodyMoverParentingFix": "True",
	"DFFlagBroadcastServerOnAllInterfaces": "True",
	"HttpUseCurlPercentageWinClient": "0",
	"HttpUseCurlPercentageWinStudio": "0",
	"SFFlagReplicatedFirstEnabled": "False",
	"DFFlagCSGShrinkForMargin": "False",
	"FFlagPhysicsBulletConnectorPointRecalc": "False",
	"DFIntBulletContactBreakThresholdPercent": "200",
	"DFIntBulletContactBreakOrthogonalThresholdPercent": "1000",
	"FFlagPhysicsBulletConnectorMatching": "False",
	"FFlagPhysicsBulletUseProximityMatching": "False",
	"FFlagPhysicsCSGUsesBullet": "False",
	"DFFlagCSGPhysicsDeserializeRefactor": "False",
	"FFlagWedgeEnableDecalOnTop": "True",
	"FFlagFrustumTestGUI": "True",
	"FFlagFeatureLvlsDX11BeforeDeviceCreate": "True",
	"FFlagStudioPasteSyncEnabled": "True",
	"FFlagResetMouseCursorOnToolUnequip": "True",
	"DFFlagUpdateCameraTarget": "True",
	"DFFlagFixGhostClimb": "False",
	"DFFlagUseStarterPlayer": "True",
	"FFlagSingleNewton": "True",
	"FFlagStudioMobileEmulatorEnabled": "True",
	"FFlagStudioFindCrashFixEnabled": "True",
	"FFlagFixPartOffset": "True",
	"DFFlagLuaCloseUpvalues": "True",
	"FFlagRenderTextureCompositorUseBudgetForSize": "True",
	"FFlagAllowOutOfBoxAssets": "False",
	"FFlagRemoveTintingWhenActiveIsFalseOnImageButton": "True",
	"FFlagStudioModuleScriptDefaultContents": "True",
	"FFlagStudioHomeKeyChangeEnabled": "True",
	"FFlagStudioOpenStartPageForLogin": "True",
	"FFlagStudioNativeKeepSavedChanges": "True",
	"FFlagSerializeCurrentlyOpenPlaceWhenPublishingGame": "True",
	"FFlagGameNameLabelEnabled": "True",
	"FFlagStudioValidateBootstrapper": true,
	"FFlagRakNetReadFast": "True",
	"DFFlagPhysicsSenderSleepingUpdate": "True",
	"FFlagUseShortShingles": "True",
	"FFlagFastLPSolver": "True",
	"FFlagKKTChecks": "False",
	"DFFlagUseApiProxyThrottling": "True",
	"FFlagNewLoadingScreen": "True",
	"FFlagDebugLocalRccServerConnection": "True"
}
